odoo10_addon_mrp_bom_structure_xlsx_level_1-10.0.1.0.0-py2.7-nspkg.pth
odoo/addons/mrp_bom_structure_xlsx_level_1/README.rst
odoo/addons/mrp_bom_structure_xlsx_level_1/__init__.py
odoo/addons/mrp_bom_structure_xlsx_level_1/__manifest__.py
odoo/addons/mrp_bom_structure_xlsx_level_1/i18n/de.po
odoo/addons/mrp_bom_structure_xlsx_level_1/report/__init__.py
odoo/addons/mrp_bom_structure_xlsx_level_1/report/bom_structure_xlsx.py
odoo/addons/mrp_bom_structure_xlsx_level_1/report/bom_structure_xlsx.xml
odoo/addons/mrp_bom_structure_xlsx_level_1/static/description/icon.png
odoo/addons/mrp_bom_structure_xlsx_level_1/static/description/index.html
odoo10_addon_mrp_bom_structure_xlsx_level_1-10.0.1.0.0.dist-info/DESCRIPTION.rst
odoo10_addon_mrp_bom_structure_xlsx_level_1-10.0.1.0.0.dist-info/METADATA
odoo10_addon_mrp_bom_structure_xlsx_level_1-10.0.1.0.0.dist-info/RECORD
odoo10_addon_mrp_bom_structure_xlsx_level_1-10.0.1.0.0.dist-info/WHEEL
odoo10_addon_mrp_bom_structure_xlsx_level_1-10.0.1.0.0.dist-info/metadata.json
odoo10_addon_mrp_bom_structure_xlsx_level_1-10.0.1.0.0.dist-info/namespace_packages.txt
odoo10_addon_mrp_bom_structure_xlsx_level_1-10.0.1.0.0.dist-info/top_level.txt
